.pre-commit-config.yaml
.travis.yml
AUTHORS
ChangeLog
LICENSE
README.md
pyproject.toml
requirements-dev.txt
requirements.txt
setup.cfg
setup.py
flask_observability/__init__.py
flask_observability.egg-info/PKG-INFO
flask_observability.egg-info/SOURCES.txt
flask_observability.egg-info/dependency_links.txt
flask_observability.egg-info/not-zip-safe
flask_observability.egg-info/pbr.json
flask_observability.egg-info/requires.txt
flask_observability.egg-info/top_level.txt
tests/test_extension.py