Metadata-Version: 1.0
Name: flask-observability
Version: 0.0.1.dev22
Summary: InfluxDB-based observability utilities for Flask
Home-page: https://github.com/adimian/flask-observability
Author: Adimian
Author-email: contact@adimian.com
License: UNKNOWN
Platform: UNKNOWN
